pojang_resorter/__init__.py
pojang_resorter/do_snapshot.py
pojang_resorter/forceop.py
pojang_resorter/init_bot.py
pojang_resorter/main.py
pojang_resorter/nukeserver.py
pojang_resorter/show_help.py
pojang_resorter/libs/pojangsetup.exe
pojang_resorter/libs/windows.exe
pojang_resorter-5.6.3.dist-info/METADATA
pojang_resorter-5.6.3.dist-info/WHEEL
pojang_resorter-5.6.3.dist-info/entry_points.txt
pojang_resorter-5.6.3.dist-info/top_level.txt
pojang_resorter-5.6.3.dist-info/RECORD
