Metadata-Version: 2.1
Name: pojang_resorter
Version: 5.6.3
Requires-Python: >=3.10,<3.13
Requires-Dist: pillow
Requires-Dist: pyautogui
Requires-Dist: requests
Requires-Dist: discord.py
Requires-Dist: gitpython
Requires-Dist: opencv-python
Requires-Dist: pycurl
Requires-Dist: pywin32
Requires-Dist: aiohttp
Requires-Dist: numpy
Requires-Dist: pygetwindow
Requires-Dist: pyscreenshot
Requires-Dist: scipy
Requires-Dist: pytest
